PersonalAssistant/__init__.py
PersonalAssistant-0.0.1.dist-info/LICENSE
PersonalAssistant-0.0.1.dist-info/METADATA
PersonalAssistant-0.0.1.dist-info/WHEEL
PersonalAssistant-0.0.1.dist-info/top_level.txt
PersonalAssistant-0.0.1.dist-info/RECORD
