Metadata-Version: 2.1
Name: PersonalAssistant
Version: 0.0.1
Summary: A package for starting you assistant using python
Home-page: https://github.com/pypa/PersonalAssistant
Author: Debadrito Dutta
Author-email: dipalidutta312@gmail.com
License: UNKNOWN
Project-URL: Bug Tracker, https://github.com/pypa/PersonalAssistant/issues
Platform: UNKNOWN
Classifier: Programming Language :: Python :: 3
Classifier: License :: OSI Approved :: MIT License
Classifier: Operating System :: OS Independent
Requires-Python: >=3.4
